[{"totalLoad":71,"Departing":"HSB","CaptureDate":"2019-09-24","sailingTime":"0730","dayofWeek":"2"},{"totalLoad":59,"Departing":"HSB","CaptureDate":"2019-09-24","sailingTime":"0950","dayofWeek":"2"},{"totalLoad":91,"Departing":"HSB","CaptureDate":"2019-09-24","sailingTime":"1205","dayofWeek":"2"},{"totalLoad":95,"Departing":"HSB","CaptureDate":"2019-09-24","sailingTime":"1420","dayofWeek":"2"},{"totalLoad":91,"Departing":"HSB","CaptureDate":"2019-09-24","sailingTime":"1640","dayofWeek":"2"},{"totalLoad":30,"Departing":"HSB","CaptureDate":"2019-09-24","sailingTime":"1730","dayofWeek":"2"},{"totalLoad":48,"Departing":"HSB","CaptureDate":"2019-09-24","sailingTime":"1855","dayofWeek":"2"},{"totalLoad":30,"Departing":"HSB","CaptureDate":"2019-09-24","sailingTime":"2110","dayofWeek":"2"},{"totalLoad":1,"Departing":"HSB","CaptureDate":"2019-09-24","sailingTime":"2320","dayofWeek":"2"},{"totalLoad":73,"Departing":"HSB","CaptureDate":"2019-09-25","sailingTime":"0730","dayofWeek":"3"},{"totalLoad":58,"Departing":"HSB","CaptureDate":"2019-09-25","sailingTime":"0950","dayofWeek":"3"},{"totalLoad":94,"Departing":"HSB","CaptureDate":"2019-09-25","sailingTime":"1205","dayofWeek":"3"},{"totalLoad":96,"Departing":"HSB","CaptureDate":"2019-09-25","sailingTime":"1420","dayofWeek":"3"},{"totalLoad":99,"Departing":"HSB","CaptureDate":"2019-09-25","sailingTime":"1640","dayofWeek":"3"},{"totalLoad":38,"Departing":"HSB","CaptureDate":"2019-09-25","sailingTime":"1730","dayofWeek":"3"},{"totalLoad":40,"Departing":"HSB","CaptureDate":"2019-09-25","sailingTime":"1855","dayofWeek":"3"},{"totalLoad":41,"Departing":"HSB","CaptureDate":"2019-09-25","sailingTime":"2110","dayofWeek":"3"},{"totalLoad":6,"Departing":"HSB","CaptureDate":"2019-09-25","sailingTime":"2320","dayofWeek":"3"},{"totalLoad":72,"Departing":"HSB","CaptureDate":"2019-09-26","sailingTime":"0730","dayofWeek":"4"},{"totalLoad":80,"Departing":"HSB","CaptureDate":"2019-09-26","sailingTime":"0950","dayofWeek":"4"},{"totalLoad":95,"Departing":"HSB","CaptureDate":"2019-09-26","sailingTime":"1205","dayofWeek":"4"}]
